elevenlabs_haystack/__init__.py
elevenlabs_haystack/component.py
elevenlabs_haystack-0.4.5.dist-info/METADATA
elevenlabs_haystack-0.4.5.dist-info/WHEEL
elevenlabs_haystack-0.4.5.dist-info/RECORD
