Metadata-Version: 2.1
Name: elevenlabs-haystack
Version: 0.4.5
Summary: ElevenLabs Text-to-Speech components for Haystack.
Author: Andy
Author-email: andychert@protonmail.com
Requires-Python: >=3.8,<4.0
Classifier: Programming Language :: Python :: 3
Classifier: Programming Language :: Python :: 3.8
Classifier: Programming Language :: Python :: 3.9
Classifier: Programming Language :: Python :: 3.10
Classifier: Programming Language :: Python :: 3.11
Classifier: Programming Language :: Python :: 3.12
Classifier: Programming Language :: Python :: 3.13
Requires-Dist: elevenlabs-s3 (>=0.3.2,<0.4.0)
Requires-Dist: haystack-ai (>=2.6.0,<3.0.0)
Requires-Dist: numpy (>=1.21.0,<2.0.0) ; python_version < "3.9"
Requires-Dist: numpy (>=1.26.0,<2.0.0) ; python_version >= "3.9"
Requires-Dist: pytest-dotenv (>=0.5.2,<0.6.0)
